pubsubsuperfeedr.py
pubsubsuperfeedr-0.4.0.dist-info/METADATA
pubsubsuperfeedr-0.4.0.dist-info/RECORD
pubsubsuperfeedr-0.4.0.dist-info/WHEEL
pubsubsuperfeedr-0.4.0.dist-info/top_level.txt
