Metadata-Version: 2.1
Name: pubsubsuperfeedr
Version: 0.4.0
Summary: Library for working with Superfeedr's PubSubHubbub API
Home-page: http://github.com/urbanairship/pubsubsuperfeedr/
Author: Urban Airship
Author-email: web-team@urbanairship.com
License: MIT License
Platform: UNKNOWN
Classifier: License :: OSI Approved :: MIT License
Classifier: Intended Audience :: Developers
Classifier: Operating System :: OS Independent
Classifier: Programming Language :: Python :: 2
Classifier: Programming Language :: Python :: 2.7
Classifier: Programming Language :: Python :: 3
Classifier: Programming Language :: Python :: 3.4
Classifier: Programming Language :: Python :: 3.5
Classifier: Programming Language :: Python :: 3.6
Classifier: Programming Language :: Python :: 3.7
Classifier: Programming Language :: Python
Classifier: Topic :: Software Development
Requires-Dist: feedparser
Requires-Dist: python-dateutil
Requires-Dist: six
